bgdata/__init__.py
bgdata/bgdata.conf.template.spec
bgdata/bgdatav2.conf.template
bgdata/bgdatav2.conf.template.spec
bgdata/builds.conf.template
bgdata/builds.conf.template.spec
bgdata/command.py
bgdata/configobj.py
bgdata/errors.py
bgdata/manager.py
bgdata/package.py
bgdata/repository.py
bgdata/tag.py
bgdata/utils.py
tests/__init__.py
tests/manager.py
tests/run.py
tests/tar.py
bgdata-2.0.4.dist-info/LICENSE.txt
bgdata-2.0.4.dist-info/METADATA
bgdata-2.0.4.dist-info/WHEEL
bgdata-2.0.4.dist-info/entry_points.txt
bgdata-2.0.4.dist-info/top_level.txt
bgdata-2.0.4.dist-info/RECORD
