Metadata-Version: 2.1
Name: bgdata
Version: 2.0.4
Summary: Simple data repository managment.
Home-page: https://bitbucket.org/bgframework/bgdata
Author: Barcelona Biomedical Genomics Lab
Author-email: UNKNOWN
License: Apache License 2
Download-URL: https://bitbucket.org/bgframework/bgdata/get/2.0.4.tar.gz
Keywords: data,managment,repository
Platform: UNKNOWN
Requires-Dist: bgconfig (>=0.8)
Requires-Dist: click
Requires-Dist: configobj
Requires-Dist: homura (>=0.1.3)
Requires-Dist: pycurl
Requires-Dist: requests
